LICENSE
suppenloffel/__init__.py
suppenloffel/imgs_scraper.py
suppenloffel/table_scraper.py
suppenloffel-0.2.5.2.dist-info/LICENSE
suppenloffel-0.2.5.2.dist-info/WHEEL
suppenloffel-0.2.5.2.dist-info/METADATA
suppenloffel-0.2.5.2.dist-info/RECORD
